geniusrise/__init__.py
geniusrise/logging.py
geniusrise/cli/__init__.py
geniusrise/cli/boltctl.py
geniusrise/cli/discover.py
geniusrise/cli/dockerctl.py
geniusrise/cli/geniusctl.py
geniusrise/cli/schema.py
geniusrise/cli/spoutctl.py
geniusrise/cli/yamlctl.py
geniusrise/core/__init__.py
geniusrise/core/bolt.py
geniusrise/core/spout.py
geniusrise/core/data/__init__.py
geniusrise/core/data/batch_input.py
geniusrise/core/data/batch_output.py
geniusrise/core/data/input.py
geniusrise/core/data/output.py
geniusrise/core/data/streaming_input.py
geniusrise/core/data/streaming_output.py
geniusrise/core/state/__init__.py
geniusrise/core/state/base.py
geniusrise/core/state/dynamo.py
geniusrise/core/state/memory.py
geniusrise/core/state/postgres.py
geniusrise/core/state/redis.py
geniusrise/core/task/__init__.py
geniusrise/core/task/base.py
geniusrise/runners/__init__.py
geniusrise/runners/airflow/__init__.py
geniusrise/runners/airflow/generate.py
geniusrise/runners/docker/__init__.py
geniusrise/runners/docker/base.py
geniusrise/runners/docker/swarm.py
geniusrise/runners/k8s/__init__.py
geniusrise/runners/k8s/base.py
geniusrise/runners/k8s/cron_job.py
geniusrise/runners/k8s/deployment.py
geniusrise/runners/k8s/job.py
geniusrise/runners/k8s/service.py
geniusrise/utils/__init__.py
geniusrise/utils/parse_function_args.py
geniusrise-0.1.7.dist-info/LICENSE
geniusrise-0.1.7.dist-info/METADATA
geniusrise-0.1.7.dist-info/WHEEL
geniusrise-0.1.7.dist-info/entry_points.txt
geniusrise-0.1.7.dist-info/top_level.txt
geniusrise-0.1.7.dist-info/RECORD
